QA_automation_phone/__init__.py
QA_automation_phone/config.py
QA_automation_phone/coreapp.py
QA_automation_phone/identify_image.py
QA_automation_phone/identify_letter.py
QA_automation_phone/keyevent.py
QA_automation_phone/script.py
QA_automation_phone/setting.py
qa_automation_phone-0.1.6.dist-info/LICENSE
qa_automation_phone-0.1.6.dist-info/METADATA
qa_automation_phone-0.1.6.dist-info/WHEEL
qa_automation_phone-0.1.6.dist-info/top_level.txt
qa_automation_phone-0.1.6.dist-info/RECORD
