Metadata-Version: 2.2
Name: QA_automation_phone
Version: 0.1.6
Summary: Automation test for phone
Author-email: Thoang <nhothoang@gmail.com>
License: GPL-3.0-only
Project-URL: Documentation, https://github.com/NhoThoang/QA_phone_automation/blob/main/README.md
Project-URL: Source, https://github.com/NhoThoang/QA_phone_automation.git
Project-URL: Tracker, https://github.com/NhoThoang/QA_phone_automation/issues
License-File: LICENSE
Requires-Dist: uiautomator2>=3.2.8
Requires-Dist: pytesseract>=0.3.13
Requires-Dist: opencv-python-headless>=4.11.0.86
